[
    {
        "id": "s00000992",
        "speaker": "system",
        "intent": "肯定する",
        "slots": {
            "観光地のジャンル": "スケート",
            "観光地が雨天でも楽しめるか": "不可能"
        }
    },
    {
        "id": "s00000452",
        "speaker": "system",
        "intent": "肯定する",
        "slots": {
            "ユーザが希望する交通手段": "車",
            "ユーザが希望する食べ物": "インドカレー"
        }
    },
    {
        "id": "s00002692",
        "speaker": "system",
        "intent": "教える",
        "slots": {
            "観光地の撮影可否": "不明",
            "観光地がインドアかアウトドアか": "アウトドア"
        }
    },
    {
        "id": "s00002117",
        "speaker": "system",
        "intent": "教える",
        "slots": {
            "観光地での観光の所要時間": "60分以上90分未満",
            "観光地が雨天でも楽しめるか": "不明"
        }
    },
    {
        "id": "s00002568",
        "speaker": "system",
        "intent": "教える",
        "slots": {
            "観光地の手荷物預かりの有無": "なし",
            "観光地がインドアかアウトドアか": "インドア"
        }
    },
    {
        "id": "s00002386",
        "speaker": "system",
        "intent": "教える",
        "slots": {
            "観光地の設備": "不明",
            "観光地のおすすめイベント": "不明"
        }
    },
    {
        "id": "s00000132",
        "speaker": "system",
        "intent": "肯定する",
        "slots": {
            "ユーザの名前": "今井",
            "ユーザの本日の同行者": "ペット"
        }
    },
    {
        "id": "s00002515",
        "speaker": "system",
        "intent": "教える",
        "slots": {
            "観光地の手荷物預かりの有無": "あり",
            "観光地の予約要否": "不可能"
        }
    },
    {
        "id": "s00000873",
        "speaker": "system",
        "intent": "肯定する",
        "slots": {
            "ユーザの本日の同行者": "カップル",
            "ユーザの本日の交通手段": "徒歩"
        }
    },
    {
        "id": "s00003199",
        "speaker": "system",
        "intent": "観光地をお勧めする",
        "slots": {
            "観光地におすすめな人": "カップル",
            "観光地におすすめな時期": "夏"
        }
    },
    {
        "id": "s00002208",
        "speaker": "system",
        "intent": "教える",
        "slots": {
            "観光地の割引": "子供とお年寄り、障害を持つ方に対して割引がある",
            "観光地の設備": "なし"
        }
    },
    {
        "id": "s00000061",
        "speaker": "system",
        "intent": "肯定する",
        "slots": {
            "ユーザの希望の観光時間帯": "朝"
        }
    },
    {
        "id": "s00000560",
        "speaker": "system",
        "intent": "肯定する",
        "slots": {
            "ユーザが希望する交通手段": "未定",
            "ユーザの希望の観光時間帯": "夜"
        }
    },
    {
        "id": "s00002268",
        "speaker": "system",
        "intent": "教える",
        "slots": {
            "観光地の設備": "乳幼児",
            "観光地の手荷物預かりの有無": "なし"
        }
    },
    {
        "id": "s00003022",
        "speaker": "system",
        "intent": "観光地をお勧めする",
        "slots": {
            "観光地の営業時間": "9時～16時30分",
            "観光地におすすめな人": "友達"
        }
    },
    {
        "id": "s00000893",
        "speaker": "system",
        "intent": "肯定する",
        "slots": {
            "ユーザの本日の同行者": "歴史好き",
            "ユーザの本日の交通手段": "徒歩"
        }
    },
    {
        "id": "s00003080",
        "speaker": "system",
        "intent": "観光地をお勧めする",
        "slots": {
            "観光地の公共交通機関でのアクセス": "大阪メトロ動物園前駅→徒歩5分。",
            "観光地におすすめな人": "カップル"
        }
    },
    {
        "id": "s00000249",
        "speaker": "system",
        "intent": "肯定する",
        "slots": {
            "ユーザの観光の同行者": "カップル",
            "ユーザが希望する観光の季節": "冬"
        }
    },
    {
        "id": "s00003211",
        "speaker": "system",
        "intent": "観光地をお勧めする",
        "slots": {
            "観光地におすすめな人": "友達",
            "観光地が雨天でも楽しめるか": "可能"
        }
    },
    {
        "id": "s00002339",
        "speaker": "system",
        "intent": "教える",
        "slots": {
            "観光地の設備": "不明",
            "観光地の喫煙可否": "可能"
        }
    }
]